odoo/addons/mrp_subcontracting_purchase_partner_management/README.rst
odoo/addons/mrp_subcontracting_purchase_partner_management/__init__.py
odoo/addons/mrp_subcontracting_purchase_partner_management/__manifest__.py
odoo/addons/mrp_subcontracting_purchase_partner_management/i18n/es.po
odoo/addons/mrp_subcontracting_purchase_partner_management/i18n/it.po
odoo/addons/mrp_subcontracting_purchase_partner_management/i18n/mrp_subcontracting_purchase_partner_management.pot
odoo/addons/mrp_subcontracting_purchase_partner_management/models/__init__.py
odoo/addons/mrp_subcontracting_purchase_partner_management/models/res_partner.py
odoo/addons/mrp_subcontracting_purchase_partner_management/readme/DESCRIPTION.rst
odoo/addons/mrp_subcontracting_purchase_partner_management/static/description/icon.png
odoo/addons/mrp_subcontracting_purchase_partner_management/static/description/index.html
odoo/addons/mrp_subcontracting_purchase_partner_management/tests/__init__.py
odoo/addons/mrp_subcontracting_purchase_partner_management/tests/test_create_subcontractor_partner_location.py
odoo14_addon_mrp_subcontracting_purchase_partner_management-14.0.1.0.1.dist-info/METADATA
odoo14_addon_mrp_subcontracting_purchase_partner_management-14.0.1.0.1.dist-info/WHEEL
odoo14_addon_mrp_subcontracting_purchase_partner_management-14.0.1.0.1.dist-info/top_level.txt
odoo14_addon_mrp_subcontracting_purchase_partner_management-14.0.1.0.1.dist-info/RECORD
